Metadata-Version: 1.0
Name: hendrix-distributions
Version: 0.1
Summary: Gaussian and Binomial distributions
Home-page: UNKNOWN
Author: Hendrix Ebrudu
Author-email: hendrixobuks@gmail.com
License: UNKNOWN
Platform: UNKNOWN
